{"docId":"XIN_ENG_20090929.0071","headline":"S.Korean, DPRK separated families' reunions enter second segment","named_entity":{"Kim Yu - jung":[[6,"PERSON",5,8]],"Red Cross":[[9,"ORGANIZATION",8,9]],"South Koreans":[[10,"MISC",2,3]],"Democratic People 's Republic of Korea":[[2,"LOCATION",16,21]],"South Korea":[[3,"LOCATION",10,11],[14,"LOCATION",13,14]],"South Korean":[[3,"MISC",2,3],[8,"MISC",4,5]],"Seoul":[[14,"LOCATION",10,10]],"day":[[3,"TIME",19,19]],"Pyongyang":[[14,"LOCATION",8,8]],"Korean War":[[11,"MISC",10,11]],"DPRK":[[1,"ORGANIZATION",3,3],[2,"ORGANIZATION",23,23],[4,"ORGANIZATION",9,9],[6,"ORGANIZATION",22,22],[10,"ORGANIZATION",14,14],[15,"ORGANIZATION",12,12]],"Korean":[[11,"MISC",20,20]],"Sokcho":[[3,"LOCATION",7,7]],"morning":[[4,"TIME",14,14]],"Yonhap":[[6,"ORGANIZATION",24,24]],"afternoon":[[7,"TIME",11,11]],"Mount Kumgang":[[2,"LOCATION",28,29],[4,"LOCATION",4,5]],"Lee Myung-bak":[[14,"PERSON",20,21]]},"cluster_json":[[{"sent_ind":2,"word":"second","mention_type":"PROPER","token_ind":33,"end_ind":34},{"sent_ind":1,"word":"second","mention_type":"PROPER","token_ind":9,"end_ind":10}],[{"sent_ind":1,"word":"S.Korean , DPRK","mention_type":"PROPER","token_ind":1,"end_ind":4},{"sent_ind":10,"word":"DPRK","mention_type":"PROPER","token_ind":14,"end_ind":15},{"sent_ind":10,"word":"the DPRK","mention_type":"PROPER","token_ind":13,"end_ind":15},{"sent_ind":2,"word":"DPRK","mention_type":"PROPER","token_ind":23,"end_ind":24},{"sent_ind":15,"word":"the DPRK","mention_type":"PROPER","token_ind":11,"end_ind":13},{"sent_ind":6,"word":"DPRK","mention_type":"PROPER","token_ind":22,"end_ind":23},{"sent_ind":6,"word":"the DPRK","mention_type":"PROPER","token_ind":21,"end_ind":23},{"sent_ind":4,"word":"the DPRK 's","mention_type":"PROPER","token_ind":8,"end_ind":11}],[{"sent_ind":10,"word":"their","mention_type":"PRONOMINAL","token_ind":9,"end_ind":10},{"sent_ind":8,"word":"the families","mention_type":"NOMINAL","token_ind":12,"end_ind":14},{"sent_ind":1,"word":"families '","mention_type":"NOMINAL","token_ind":5,"end_ind":7},{"sent_ind":2,"word":"their","mention_type":"PRONOMINAL","token_ind":11,"end_ind":12}],[{"sent_ind":4,"word":"Mount Kumgang","mention_type":"PROPER","token_ind":4,"end_ind":6},{"sent_ind":2,"word":"Mount Kumgang","mention_type":"PROPER","token_ind":28,"end_ind":30}],[{"sent_ind":4,"word":"Tuesday","mention_type":"PROPER","token_ind":13,"end_ind":14},{"sent_ind":2,"word":"Tuesday","mention_type":"PROPER","token_ind":26,"end_ind":27}],[{"sent_ind":10,"word":"the reunions","mention_type":"NOMINAL","token_ind":22,"end_ind":24},{"sent_ind":2,"word":"ongoing family reunions","mention_type":"NOMINAL","token_ind":36,"end_ind":39}],[{"sent_ind":3,"word":"a South Korea 's eastern coastal border town","mention_type":"NOMINAL","token_ind":9,"end_ind":17},{"sent_ind":3,"word":"Sokcho","mention_type":"PROPER","token_ind":7,"end_ind":8}],[{"sent_ind":4,"word":"They","mention_type":"PRONOMINAL","token_ind":1,"end_ind":2},{"sent_ind":3,"word":"The South Korean families","mention_type":"NOMINAL","token_ind":1,"end_ind":5}],[{"sent_ind":14,"word":"South Korea 's","mention_type":"PROPER","token_ind":13,"end_ind":16},{"sent_ind":3,"word":"a South Korea 's","mention_type":"PROPER","token_ind":9,"end_ind":13}],[{"sent_ind":5,"word":"the participants","mention_type":"NOMINAL","token_ind":3,"end_ind":5},{"sent_ind":5,"word":"their","mention_type":"PRONOMINAL","token_ind":7,"end_ind":8}],[{"sent_ind":7,"word":"first","mention_type":"PROPER","token_ind":2,"end_ind":3},{"sent_ind":10,"word":"first","mention_type":"PROPER","token_ind":18,"end_ind":19}],[{"sent_ind":12,"word":"two","mention_type":"PROPER","token_ind":5,"end_ind":6},{"sent_ind":11,"word":"two","mention_type":"PROPER","token_ind":24,"end_ind":25}],[{"sent_ind":14,"word":"The program","mention_type":"NOMINAL","token_ind":1,"end_ind":3},{"sent_ind":11,"word":"The reunion program of families separated by the 1950-53 Korean War","mention_type":"NOMINAL","token_ind":1,"end_ind":12}],[{"sent_ind":12,"word":"the two sides","mention_type":"NOMINAL","token_ind":4,"end_ind":7},{"sent_ind":11,"word":"the two sides","mention_type":"NOMINAL","token_ind":23,"end_ind":26}]],"text":[["S.Korean",",","DPRK","separated","families","'","reunions","enter","second","segment","."],["A","group","of","431","South","Koreans","are","expected","to","meet","their","long-lost","relatives","in","the","Democratic","People","'s","Republic","of","Korea","-LRB-","DPRK","-RRB-","on","Tuesday","at","Mount","Kumgang","resort","during","the","second","segment","of","ongoing","family","reunions","."],["The","South","Korean","families","arrived","in","Sokcho",",","a","South","Korea","'s","eastern","coastal","border","town",",","a","day","earlier","to","make","final","registrations","and","receive","orientation","."],["They","headed","to","Mount","Kumgang","resort","on","the","DPRK","'s","east","coast","Tuesday","morning","."],["Most","of","the","participants","were","in","their","70s","to","90s","."],["The","oldest","one","is","Kim","Yu","-","jung",",","100","years","old",",","who","will","meet","her","75-year-old","daughter","in","the","DPRK",",","Yonhap","news","agency","reported","."],["The","first","two-hour","reunion","session","will","be","held","in","the","afternoon","."],["Then",",","the","South","Korean","government","will","host","a","banquet","for","the","families","."],["The","three-day","event",",","arranged","by","the","Red","Cross","offices","of","both","sides",",","will","also","include","four","more","reunion","sessions","."],["Ninety-seven","South","Koreans","on","Monday","parted","ways","with","their","233","relatives","in","the","DPRK",",","as","the","first","three-day","segment","of","the","reunions","wrapped","up","."],["The","reunion","program","of","families","separated","by","the","1950-53","Korean","War","began","in","2000","after","a","historic","inter","-","Korean","summit","between","the","two","sides","."],["Since","then",",","the","two","sides","have","held","16","rounds","of","face-to-face","reunions","and","seven","rounds","of","video","exchanges","."],["The","last","reunions","were","held","in","October","2007","."],["The","program","was","suspended","as","ties","between","Pyongyang","and","Seoul","soured","after","South","Korea","'s","conservative","government","under","President","Lee","Myung-bak","came","to","power","in","February","2008","."],["About","600,000","South","Koreans","are","believed","to","have","relatives","in","the","DPRK","."]],"part_of_speech":[["NNP",",","NNP","VBD","NNS","POS","NNS","VBP","JJ","NN","."],["DT","NN","IN","CD","NNP","NNPS","VBP","VBN","TO","VB","PRP$","JJ","NNS","IN","DT","JJ","NNS","POS","NN","IN","NNP","-LRB-","NNP","-RRB-","IN","NNP","IN","NNP","NNP","NN","IN","DT","JJ","NN","IN","JJ","NN","NNS","."],["DT","JJ","JJ","NNS","VBN","IN","NNP",",","DT","NNP","NNP","POS","JJ","JJ","NN","NN",",","DT","NN","RB","TO","VB","JJ","NNS","CC","VB","NN","."],["PRP","VBD","TO","NNP","NNP","NN","IN","DT","NNP","POS","JJ","NN","NNP","NN","."],["JJS","IN","DT","NNS","VBD","IN","PRP$","CD","TO","CD","."],["DT","JJS","NN","VBZ","NNP","NNP",":","NN",",","CD","NNS","JJ",",","WP","MD","VB","PRP$","CD","NN","IN","DT","NNP",",","NNP","NN","NN","VBD","."],["DT","JJ","JJ","NN","NN","MD","VB","VBN","IN","DT","NN","."],["RB",",","DT","JJ","JJ","NN","MD","VB","DT","NN","IN","DT","NNS","."],["DT","JJ","NN",",","VBN","IN","DT","NNP","NNP","NNS","IN","DT","NNS",",","MD","RB","VB","CD","JJR","NN","NNS","."],["CD","NNP","NNPS","IN","NNP","VBD","NNS","IN","PRP$","CD","NNS","IN","DT","NNP",",","IN","DT","JJ","JJ","NN","IN","DT","NNS","VBD","RP","."],["DT","NN","NN","IN","NNS","VBN","IN","DT","CD","JJ","NN","VBD","IN","CD","IN","DT","JJ","NN",":","JJ","NN","IN","DT","CD","NNS","."],["IN","RB",",","DT","CD","NNS","VBP","VBN","CD","NNS","IN","JJ","NNS","CC","CD","NNS","IN","NN","NNS","."],["DT","JJ","NNS","VBD","VBN","IN","NNP","CD","."],["DT","NN","VBD","VBN","IN","NNS","IN","NNP","CC","NNP","VBD","IN","NNP","NNP","POS","JJ","NN","IN","NNP","NNP","NNP","VBD","TO","NN","IN","NNP","CD","."],["IN","CD","NNP","NNPS","VBP","VBN","TO","VB","NNS","IN","DT","NNP","."]],"totalParse":{"1":[[0,1,"root"],[1,2,"punct"],[1,4,"acl:relcl"],[1,11,"punct"],[4,3,"nsubj"],[4,8,"ccomp"],[5,6,"case"],[7,5,"nmod:poss"],[8,7,"nsubj"],[8,10,"dobj"],[10,9,"amod"]],"2":[[0,8,"root"],[38,35,"case"],[38,36,"amod"],[38,37,"compound"],[2,6,"nmod$of"],[2,1,"det"],[6,3,"case"],[6,4,"nummod"],[6,5,"compound"],[8,7,"auxpass"],[8,39,"punct"],[8,10,"xcomp"],[8,2,"nsubjpass"],[10,19,"nmod$in"],[10,9,"mark"],[10,26,"nmod$on"],[10,13,"dobj"],[10,30,"nmod$at"],[10,2,"nsubj"],[13,11,"nmod:poss"],[13,12,"amod"],[17,15,"det"],[17,16,"amod"],[17,18,"case"],[19,21,"nmod$of"],[19,14,"case"],[19,17,"nmod:poss"],[21,20,"case"],[21,23,"appos"],[23,22,"punct"],[23,24,"punct"],[26,25,"case"],[30,27,"case"],[30,28,"compound"],[30,29,"compound"],[30,34,"nmod$during"],[34,38,"nmod$of"],[34,31,"case"],[34,32,"det"],[34,33,"amod"]],"3":[[0,4,"root"],[7,6,"case"],[7,8,"punct"],[7,16,"appos"],[7,17,"punct"],[11,9,"det"],[11,10,"compound"],[11,12,"case"],[16,11,"nmod:poss"],[16,13,"amod"],[16,14,"amod"],[16,15,"compound"],[19,18,"det"],[20,22,"dep"],[20,26,"dep"],[20,19,"nmod:npmod"],[22,24,"dobj"],[22,25,"cc"],[22,26,"conj$and"],[22,21,"mark"],[24,23,"amod"],[26,27,"dobj"],[3,2,"amod"],[4,28,"punct"],[4,1,"det"],[4,3,"amod"],[4,20,"advmod"],[4,5,"acl"],[5,7,"nmod$in"]],"4":[[0,2,"root"],[9,10,"case"],[9,8,"det"],[12,9,"nmod:poss"],[12,11,"amod"],[12,7,"case"],[14,13,"compound"],[2,14,"nmod:tmod"],[2,15,"punct"],[2,1,"nsubj"],[2,6,"nmod$to"],[6,12,"nmod$on"],[6,3,"case"],[6,4,"compound"],[6,5,"compound"]],"5":[[0,8,"root"],[1,4,"nmod$of"],[4,2,"case"],[4,3,"det"],[8,1,"nsubj"],[8,5,"cop"],[8,6,"case"],[8,7,"nmod:poss"],[8,10,"nmod$to"],[8,11,"punct"],[10,9,"case"]],"6":[[0,6,"root"],[3,1,"det"],[3,2,"amod"],[6,3,"nsubj"],[6,4,"cop"],[6,5,"compound"],[6,7,"punct"],[6,27,"dep"],[6,28,"punct"],[8,16,"acl:relcl"],[8,23,"punct"],[8,9,"punct"],[8,12,"amod"],[8,13,"punct"],[8,14,"ref"],[11,10,"nummod"],[12,11,"nmod:npmod"],[16,15,"aux"],[16,19,"dobj"],[16,22,"nmod$in"],[16,8,"nsubj"],[19,17,"nmod:poss"],[19,18,"nummod"],[22,20,"case"],[22,21,"det"],[26,24,"compound"],[26,25,"compound"],[27,8,"dep"],[27,26,"nsubj"]],"7":[[0,8,"root"],[5,2,"amod"],[5,3,"amod"],[5,4,"compound"],[5,1,"det"],[8,5,"nsubjpass"],[8,6,"aux"],[8,7,"auxpass"],[8,11,"nmod$in"],[8,12,"punct"],[11,9,"case"],[11,10,"det"]],"8":[[0,8,"root"],[5,4,"amod"],[6,5,"amod"],[6,3,"det"],[8,6,"nsubj"],[8,7,"aux"],[8,10,"dobj"],[8,14,"punct"],[8,1,"advmod"],[8,2,"punct"],[10,9,"det"],[10,13,"nmod$for"],[13,11,"case"],[13,12,"det"]],"9":[[0,17,"root"],[3,14,"punct"],[3,1,"det"],[3,2,"amod"],[3,4,"punct"],[3,5,"acl"],[5,10,"nmod$by"],[10,8,"compound"],[10,9,"compound"],[10,13,"nmod$of"],[10,6,"case"],[10,7,"det"],[13,11,"case"],[13,12,"det"],[17,15,"aux"],[17,16,"advmod"],[17,3,"nsubj"],[17,21,"dobj"],[17,22,"punct"],[21,18,"nummod"],[21,19,"amod"],[21,20,"compound"]],"10":[[0,6,"root"],[3,1,"nummod"],[3,2,"compound"],[3,5,"nmod$on"],[5,4,"case"],[6,11,"nmod$with"],[6,15,"punct"],[6,3,"nsubj"],[6,7,"dobj"],[6,24,"parataxis"],[6,26,"punct"],[11,14,"nmod$in"],[11,8,"case"],[11,9,"nmod:poss"],[11,10,"nummod"],[14,12,"case"],[14,13,"det"],[20,16,"case"],[20,17,"det"],[20,18,"amod"],[20,19,"amod"],[20,23,"nmod$of"],[23,21,"case"],[23,22,"det"],[24,20,"nmod$as"],[24,25,"compound:prt"]],"11":[[0,12,"root"],[3,1,"det"],[3,2,"compound"],[3,5,"nmod$of"],[5,4,"case"],[5,6,"acl"],[6,11,"nmod$by"],[11,7,"case"],[11,8,"det"],[11,9,"nummod"],[11,10,"amod"],[12,14,"nmod$in"],[12,18,"nmod$after"],[12,3,"nsubj"],[12,26,"punct"],[14,13,"case"],[18,15,"case"],[18,16,"det"],[18,17,"amod"],[18,21,"dep"],[21,19,"punct"],[21,20,"amod"],[21,25,"nmod$between"],[25,22,"case"],[25,23,"det"],[25,24,"nummod"]],"12":[[0,8,"root"],[2,1,"case"],[6,4,"det"],[6,5,"nummod"],[8,2,"nmod$since"],[8,3,"punct"],[8,20,"punct"],[8,6,"nsubj"],[8,7,"aux"],[8,10,"dobj"],[10,9,"nummod"],[10,13,"nmod$of"],[10,16,"nmod$of"],[13,11,"case"],[13,12,"amod"],[13,14,"cc"],[13,16,"conj$and"],[16,19,"nmod$of"],[16,15,"nummod"],[19,17,"case"],[19,18,"compound"]],"13":[[0,5,"root"],[5,4,"auxpass"],[5,7,"nmod$in"],[5,9,"punct"],[5,3,"nsubjpass"],[7,6,"case"],[7,8,"nummod"],[3,1,"det"],[3,2,"amod"]],"14":[[0,4,"root"],[8,7,"case"],[8,9,"cc"],[8,10,"conj$and"],[11,22,"advcl"],[14,13,"compound"],[14,15,"case"],[17,14,"nmod:poss"],[17,16,"amod"],[17,21,"nmod$under"],[21,18,"case"],[21,19,"compound"],[21,20,"compound"],[22,24,"nmod$to"],[22,26,"nmod$in"],[22,12,"mark"],[22,17,"nsubj"],[24,23,"case"],[26,25,"case"],[26,27,"nummod"],[2,1,"det"],[4,28,"punct"],[4,2,"nsubjpass"],[4,3,"auxpass"],[4,6,"nmod$as"],[6,8,"nmod$between"],[6,10,"nmod$between"],[6,11,"acl"],[6,5,"case"]],"15":[[0,6,"root"],[12,10,"case"],[12,11,"det"],[2,1,"advmod"],[4,2,"nummod"],[4,3,"compound"],[6,13,"punct"],[6,4,"nsubjpass"],[6,5,"auxpass"],[6,8,"xcomp"],[8,4,"nsubj"],[8,7,"mark"],[8,9,"dobj"],[9,12,"nmod$in"]]},"processed":{"1":[{"edgeName":"nsubj","govWord":"separated enter","depWord":"DPRK","dep":[3],"gov":[4,8]},{"edgeName":"nsubj","govWord":"enter segment","depWord":"families reunions","dep":[5,7],"gov":[8,10]},{"edgeName":"dobj","govWord":"reunions enter","depWord":"second segment","dep":[9,10],"gov":[7,8]}],"2":[{"edgeName":"nsubjpass","govWord":"are expected meet .","depWord":"A group Koreans","dep":[1,2,6],"gov":[7,8,10,39]},{"edgeName":"dobj","govWord":"group to meet Republic Tuesday resort","depWord":"their long-lost relatives","dep":[11,12,13],"gov":[2,9,10,19,26,30]},{"edgeName":"nsubj","govWord":"to meet relatives Republic Tuesday resort","depWord":"A group Koreans","dep":[1,2,6],"gov":[9,10,13,19,26,30]},{"edgeName":"appos","govWord":"of Korea","depWord":"-LRB- DPRK -RRB-","dep":[22,23,24],"gov":[20,21]}],"3":[{"edgeName":"appos","govWord":"in Sokcho , ,","depWord":"Korea eastern coastal border town","dep":[11,13,14,15,16],"gov":[6,7,8,17]},{"edgeName":"dobj","govWord":"to make and receive","depWord":"final registrations","dep":[23,24],"gov":[21,22,25,26]},{"edgeName":"dobj","govWord":"receive","depWord":"orientation","dep":[27],"gov":[26]}],"4":[{"edgeName":"nsubj","govWord":"headed resort morning .","depWord":"They","dep":[1],"gov":[2,6,14,15]}],"5":[{"edgeName":"nsubj","govWord":"were in their 70s 90s .","depWord":"Most participants","dep":[1,4],"gov":[5,6,7,8,10,11]}],"6":[{"edgeName":"nsubj","govWord":"is Kim Yu - reported .","depWord":"The oldest one","dep":[1,2,3],"gov":[4,5,6,7,27,28]},{"edgeName":"dobj","govWord":"jung will meet DPRK","depWord":"her 75-year-old daughter","dep":[17,18,19],"gov":[8,15,16,22]},{"edgeName":"nsubj","govWord":"will meet daughter DPRK","depWord":"jung , old , who ,","dep":[8,9,12,13,14,23],"gov":[15,16,19,22]},{"edgeName":"nsubj","govWord":"jung reported","depWord":"Yonhap news agency","dep":[24,25,26],"gov":[8,27]}],"7":[{"edgeName":"nsubjpass","govWord":"will be held afternoon .","depWord":"The first two-hour reunion session","dep":[1,2,3,4,5],"gov":[6,7,8,11,12]}],"8":[{"edgeName":"nsubj","govWord":"Then , will host banquet .","depWord":"the Korean government","dep":[3,5,6],"gov":[1,2,7,8,10,14]},{"edgeName":"dobj","govWord":"Then , government will host .","depWord":"a banquet families","dep":[9,10,13],"gov":[1,2,6,7,8,14]}],"9":[{"edgeName":"nsubj","govWord":"will also include sessions .","depWord":"The three-day event , arranged ,","dep":[1,2,3,4,5,14],"gov":[15,16,17,21,22]},{"edgeName":"dobj","govWord":"event will also include .","depWord":"four more reunion sessions","dep":[18,19,20,21],"gov":[3,15,16,17,22]}],"10":[{"edgeName":"nsubj","govWord":"parted ways relatives , wrapped .","depWord":"Ninety-seven South Koreans Monday","dep":[1,2,3,5],"gov":[6,7,11,15,24,26]},{"edgeName":"dobj","govWord":"Koreans parted relatives , wrapped .","depWord":"ways","dep":[7],"gov":[3,6,11,15,24,26]}],"11":[{"edgeName":"nsubj","govWord":"began 2000 inter .","depWord":"The reunion program families","dep":[1,2,3,5],"gov":[12,14,18,26]}],"12":[{"edgeName":"nsubj","govWord":"then , have held rounds .","depWord":"the two sides","dep":[4,5,6],"gov":[2,3,7,8,10,20]},{"edgeName":"dobj","govWord":"then , sides have held .","depWord":"16 rounds reunions rounds","dep":[9,10,13,16],"gov":[2,3,6,7,8,20]}],"13":[{"edgeName":"nsubjpass","govWord":"were held October .","depWord":"The last reunions","dep":[1,2,3],"gov":[4,5,7,9]}],"14":[{"edgeName":"nsubj","govWord":"after came power February","depWord":"Korea conservative government Myung-bak","dep":[14,16,17,21],"gov":[12,22,24,26]},{"edgeName":"nsubjpass","govWord":"was suspended ties .","depWord":"The program","dep":[1,2],"gov":[3,4,6,28]}],"15":[{"edgeName":"nsubjpass","govWord":"are believed have .","depWord":"600,000 South Koreans","dep":[2,3,4],"gov":[5,6,8,13]},{"edgeName":"nsubj","govWord":"to have relatives","depWord":"600,000 South Koreans","dep":[2,3,4],"gov":[7,8,9]},{"edgeName":"dobj","govWord":"Koreans to have","depWord":"relatives DPRK","dep":[9,12],"gov":[4,7,8]}]}}